sebastes/__init__.py
sebastes/__main__.py
sebastes/logger/__init__.py
sebastes/logger/logger.py
sebastes/parser/__init__.py
sebastes/parser/parser.py
sebastes/processor/__init__.py
sebastes/processor/common.py
sebastes/processor/processor.py
sebastes/scanner/__init__.py
sebastes/scanner/scanner.py
sebastes-0.1.4.dist-info/LICENSE
sebastes-0.1.4.dist-info/METADATA
sebastes-0.1.4.dist-info/WHEEL
sebastes-0.1.4.dist-info/entry_points.txt
sebastes-0.1.4.dist-info/top_level.txt
sebastes-0.1.4.dist-info/RECORD
