Metadata-Version: 2.1
Name: sebastes
Version: 0.1.4
Summary: Pydantic library code generator for Redfish targets
Home-page: https://github.com/YADRO-KNS/sebastes
Author: Sergey Parshin
Author-email: s.parshin@yadro.com
License: MIT License
Platform: UNKNOWN
Classifier: Development Status :: 4 - Beta
Classifier: Programming Language :: Python :: 3.9
Classifier: License :: OSI Approved :: MIT License
Classifier: Operating System :: Unix
Requires-Python: >=3.9
License-File: LICENSE
Requires-Dist: datamodel-code-generator (==0.11.20)
Requires-Dist: pre-commit (==2.18.1)
Requires-Dist: requests (==2.27.1)
